model_registry_sdk/__init__.py
model_registry_sdk/registry.py
AIP_model_registry-0.1.0.dist-info/METADATA
AIP_model_registry-0.1.0.dist-info/WHEEL
AIP_model_registry-0.1.0.dist-info/top_level.txt
AIP_model_registry-0.1.0.dist-info/RECORD
