Metadata-Version: 2.1
Name: AIP-model-registry
Version: 0.1.0
Summary: A simple SDK for managing ML models
Home-page: https://github.com/AIP-MLOPS/model-registry
Author: Your Name
Author-email: your-email@example.com
Requires-Python: >=3.6
